DMem.sv
module DMem(
  input clk,
        Wen,
  input[7:0] WDat,
             Addr,
  output logic[7:0] Rdat);

  logic[7:0] core[256];

  always_ff @(posedge clk)
    if(Wen) begin
	core[Addr] <= WDat;

    end


  assign Rdat = core[WDat];

endmodule

ALU.sv
module ALU(
  input [3:0] Aluop,
  input [2:0] Imm,
  input [7:0] DatA,
              DatB,
  output logic[7:0] Rslt,
  output logic      Zero,
                    Par,
  					Jen,
  SCo);
  
  logic signed [2:0] signed_imm;

always_comb begin
  Rslt = 8'b0;
  SCo  = 8'b0;
  case(Aluop)
    4'b0000: {SCo,Rslt} = DatA ^ DatB;   // xor
    4'b0001: {SCo,Rslt} = DatA + DatB; // add
    4'b0010: {SCo,Rslt} = DatA - DatB;    // sub
    4'b0011: 
      if (DatA > 0) begin
          Rslt = 8'b00000000;
        end else begin
          Rslt = 8'b00000001;
        end  
    // Sign function
    4'b0100:  Rslt = ~DatA;   // count bits
    4'b0101: begin                      
        Rslt = 0; 
        for (int i = 0; i < 8; i++) begin
          if (DatA[i]) begin
            Rslt++;
          end
        end
      end
    4'b0110: if(DatA < DatB) begin 
            Jen = 1;
    end else begin
            Jen = 0;
    end 
    4'b0111: if(DatA < DatB) begin 
            Jen = 1;
    end else begin
            Jen = 0;
    end 
    
    4'b1000: Rslt = DatA;
    4'b1001: begin
        signed_imm = Imm;
        if (signed_imm >= 0) begin
            Rslt = DatA << signed_imm;  
        end else begin
            Rslt = DatA >> -signed_imm; 
        end
    end
    4'b1010:
    {SCo,Rslt} = DatA + Imm;
    4'b1011:
    {SCo,Rslt} = DatA - Imm;
  endcase
end

  assign Zero = !Rslt;
  assign Par  = ^Rslt;

endmodule

RegFile.sv
module RegFile(
  input      clk,	 // clock
             Wen,    // write enable
  input[2:0] Ra,     // read address pointer A
             Rb,     //                      B
			 Wd,	 // write address pointer
  input[7:0] Wdat,   // write data in
  output[7:0]RdatA,	 // read data out A
             RdatB); // read data out B

  logic[7:0] Core[8]; // reg file itself (4*8 array)

  always_ff @(posedge clk)
    if(Wen) Core[Wd] <= Wdat;

  assign RdatA = Core[Ra];
  assign RdatB = Core[Rb];
  

endmodule

Ctrl.sv
module Ctrl(
  input        [8:0] mach_code,
  input		   		 Jen, // jump flag
  output logic [3:0] Aluop,
  output logic [4:0] Jptr,
  output logic [2:0] Ra,
			         Rb,
			         Wd,
  					 Imm,
  output logic       WenR,
					 WenD,
					 Ldr,
					 Str

);

  // 876_543_210
  // 000_000_000
  
  always_comb begin
case(mach_code[8:6]) 
    3'b000: begin // Load/Store
      Ldr = !mach_code[5]; 
      Str = mach_code[5]; 
      
      if (Ldr) begin
        // load address in Ra into Wd register
        Ra = mach_code[4:2]; 
        Wd = mach_code[1:0]; 
      end else begin
		// store value in Ra into address in Wd register
        Ra = mach_code[4:3]; 
      	Wd = mach_code[2:0];
      end
      WenR = Ldr;         
      WenD = Str;       
    end
    3'b010: begin // ALU
      Aluop = {2'b00, mach_code[5:4]}; // Function code determines ALU operation
      Ra = mach_code[3:2];    // Source register 1
      Rb = mach_code[1:0];    // Source register 2
      Wd = mach_code[3:2];    // Destination register
      
      WenR = 1'b1; 
      
      if (mach_code[5:4] == 2'b11) begin
          Ra = mach_code[1:0];
          Wd = mach_code[1:0];
        if (mach_code[3:2] == 2'b00) begin
           Aluop = 4'b0011;
        end else if (mach_code[3:2] == 2'b10) begin
          Aluop = 4'b0100;
        end else if (mach_code[3:2] == 2'b01) begin
           Aluop = 4'b0101;
        end
      end
       
    end
  3'b100: begin //  Jump (brc_jump, jump)
      if (mach_code[5] == 1'b1) begin
        Jptr = mach_code[4:0];  // regular jump
      end else begin
        if (Jen) begin
          Jptr = mach_code[4:0]; // brc_jmp
        end
          
      end
    end
  	3'b101: begin // blt
      Ra = mach_code[5:3];   
      Rb = mach_code[2:0];
      Aluop = 4'b0110;
      end 
    3'b110: begin // beq
      Ra = mach_code[5:3];   
      Rb = mach_code[2:0];  
      Aluop = 4'b0111;
     end 
  	3'b001: begin // mov
      Ra = mach_code[5:3]; 
      Wd = mach_code[2:0]; 
      WenR = 1'b1;          
      Aluop = 4'b1000;
    end
  	3'b011: begin // shift
      Ra = mach_code[5:3]; 
      Imm = mach_code[2:0];
      Wd = mach_code[5:3];
      Aluop = 4'b1001;
      WenR = 1'b1; 
    end
  
    3'b111: begin // Immediate arithmetic (Addi, Subi)
      Aluop = {3'b101, mach_code[5]}; // 0 for Addi, 1 for Subi
      Ra = mach_code[4:3];    // Operand register
      Wd = mach_code[4:3];    // Destination register
      Imm = mach_code[2:0];
      WenR = 1'b1;            // Enable register write
    end
endcase
  end
endmodule

InstROM.sv
module InstROM(
  input[5:0] PC,
  output logic[8:0] mach_code);

  logic[8:0] Core[4096]; // must not exceed 2^12 entries

  initial 
    $readmemb("mach_code_prog_1.txt",Core);

  always_comb mach_code = Core[PC];

endmodule

ProgCtr.sv
module ProgCtr(
  input             clk,
                    reset,
					Jen,
  input       [5:0] Jump,
  output logic[5:0] PC);

  always_ff @(posedge clk)
    if(reset) PC <= 'b0;
	else if(Jen) PC <= Jump;
	else      PC <= PC + 6'd1;

endmodule

JLUT.sv
module JLUT(
  input[4:0] Jptr,
  output logic[5:0] Jump);

  always_comb case(Jptr)
	0: Jump = 0;  // Outer loop
	1: Jump = 7; // inner looop
	2: Jump = 42; // update_min
	3: Jump = 33; // check greater
    4: Jump = 49; //end
  endcase 

endmodule

Top.sv
module Top(
  input        clk,
		       reset, 
  output logic done);

  wire[5:0] Jump,
	        PC;
  wire[2:0] Ra,
			Rb,
			Wd;
  wire[3:0] Aluop;
  wire[2:0] Imm;    //
  wire[4:0] Jptr; // 32 possible jump entries
  wire[8:0] mach_code;
  wire[7:0] DatA,	     // ALU data in
            DatB,
			Rslt,		 // ALU data out
			RdatA,		 // RF data out
			RdatB,
			WdatR,		 // RF data in
			WdatD,		 // DM data in
			Rdat,		 // DM data out
			Addr;		 // DM address
  wire      Jen,		 // PC jump enable
            Par,         // ALU parity flag
			SCo,         // ALU shift/carry out
            Zero,        // ALU zero flag
			WenR,		 // RF write enable
			WenD,		 // DM write enable
			Ldr,		 // LOAD
			Str;		 // STORE

assign  DatA = RdatA;
assign  DatB = RdatB; 
assign  WdatR = Rslt;
  
 always_comb begin 
   if(PC == 50)begin
     done = 1;
   end
     
  end 

JLUT JL1(
  .Jptr,
  .Jump);

ProgCtr PC1(
  .clk,
  .reset,
  .Jen,
  .Jump,
  .PC);

InstROM IR1(
  .PC,
  .mach_code);

Ctrl C1(
  .mach_code,
  .Aluop,
  .Jptr,
  .Ra,
  .Rb,
  .Wd,
  .WenR,
  .WenD,
  .Ldr,
  .Str,
  .Jen,
  .Imm
);

RegFile RF1(
  .clk,
  .Wen(WenR),
  .Ra,
  .Rb,
  .Wd,
  .Wdat(WdatR),
  .RdatA,
  .RdatB
);

ALU A1(
  .Aluop,
  .DatA,
  .DatB,
  .Rslt,
  .Zero,
  .Par,
  .SCo,
  .Imm,
  .Jen
);

DMem dm(
  .clk,
  .Wen (WenD),
  .WDat(WdatD),
  .Addr,
  .Rdat);


endmodule

test_bench.sv
// program 1    CSE141L   min & max Hamming distances in double precision data pairs


module test_bench;

// connections to DUT: clock, start (request), done (acknowledge) 
  bit  clk,
       start = 'b1;
  wire done;

  logic[ 4:0] Dist, Min, Max;	// current, min, max Hamming distances
  logic[ 4:0] Min1, Min2;	 	// addresses of pair w/ smallest Hamming distance
  logic[ 4:0] Max1, Max2;		// addresses of pair w/ largest Hamming distance
  logic[15:0] Tmp[32];		    // cache of 16-bit values assembled from data_mem

  Top t1(.clk  (clk  ),	         // REPLACE DUT with TOP
         .reset(start),
		 .done (done )); 

  always begin
    #50ns clk = 'b1;
	#50ns clk = 'b0;
  end

  initial begin
     $dumpfile("dump.vcd");
   $dumpvars;  
// load operands for program 1 into data memory
// 32 double-precision operands go into data_mem [0:63]
// first operand = {data_mem[0],data_mem[1]}  
//   endian order doesn't matter for program 1, as long as consistent for all values (why?)
    #100ns;
	Min = 'd16;						         // start test bench Min at max value
	Max = 'd0;						         // start test bench Max at min value
    
    //t1.RF1.Core[0] = 0;
   // t1.RF1.Core[1] = 0;
   // t1.RF1.Core[2] = 0;
   // t1.RF1.Core[3] = 0;
    //t1.RF1.Core[4] = 0;
    /*t1.RF1.Core[5] = 0; 
    t1.RF1.Core[6] = 31;
    t1.RF1.Core[7] = 0;*/

    
    
    for(int i=0; i<32; i++) begin
      {t1.dm.core[2*i],t1.dm.core[2*i+1]} = $random;  
      Tmp[i] = {t1.dm.core[2*i],t1.dm.core[2*i+1]};
      $display("%d:  %b",i,Tmp[i]);
	end
// TODO: delete DUT data memory preloads beyond [63] (next 3 lines of code)
    t1.dm.core[64] = 'd16;		             // preset DUT final Min to max possible
    for(int r=65; r<256; r++)
	  t1.dm.core[r] = 'd0;		             // preset DUT final Max to min possible 
// 	compute correct answers
    for(int j=0; j<32; j++) begin
      for(int k=j+1; k<32; k++) begin
	    #1ns Dist = ham(Tmp[j],Tmp[k]);
        if(Dist<Min) begin                   // update Hamming minimum
          Min = Dist;						 //   value
		  Min2 = j;							 //	  location of data pair
		  Min1 = k;							 //         "
		end  
		if(Dist>Max) begin 			         // update Hamming maximum
		  Max = Dist;						 //   value
		  Max2 = j;							 //   location of data pair
		  Max1 = k;							 //			"
        end
	  end
    end   
	#200ns start = 'b0; 
    #200ns wait (done);						 // avoid false done signals on startup

// check results in data_mem[64] and [65] (Minimum and Maximum distances, respectively)
    if(Min == t1.dm.core[64]) $display("good Min = %d",Min);
	else                      $display("fail Min = %d",Min);
                              $display("Min addr = %d, %d",Min1, Min2);
							  $display("Min valu = %b, %b",Tmp[Min1],Tmp[Min2]);//{D1.dm.core[2*Min1],D1.dm.core[2*Min1+1]},{D1.dm.core[2*Min2],D1.dm.core[2*Min2+1]});
    if(Max == t1.dm.core[65]) $display("good Max = %d",Max);
	else                      $display("MAD  Max = %d",Max);
	                          $display("Max pair = %d, %d",Max1, Max2);
							  $display("Max valu = %b, %b",Tmp[Max1],Tmp[Max2]);//{D1.dm.core[2*Max1],D1.dm.core[2*Max1+1]},{D1.dm.core[2*Max2],D1.dm.core[2*Max2+1]});
    #200ns start = 'b1;
// to do: load operands for program 2 into data memory (reuse program 1 operands is fine here)
	#200ns start = 'b0;
	$stop;
  end

// Hamming distance (anticorrelation) between two 16-bit numbers 
  function[4:0] ham(input[15:0] a, b);
    ham = 'b0;
    for(int q=0;q<16;q++)
      if(a[q]^b[q]) ham++;	                // count number of bits for which a[i] = !b[i]
  endfunction

endmodule

dump.vcd
$date
	Fri May 17 13:06:23 2024
$end
$version
	QuestaSim Version 2023.1
$end
$timescale
	1ns
$end

$scope module test_bench $end
$var wire 1 ! done $end
$var reg 5 " Dist [4:0] $end
$var reg 5 # Max [4:0] $end
$var reg 5 $ Max1 [4:0] $end
$var reg 5 % Max2 [4:0] $end
$var reg 5 & Min [4:0] $end
$var reg 5 ' Min1 [4:0] $end
$var reg 5 ( Min2 [4:0] $end
$var reg 1 ) clk $end
$var reg 1 * start $end

$scope function ham $end
$var reg 16 + a [15:0] $end
$var reg 16 , b [15:0] $end
$var reg 5 - ham [4:0] $end
$upscope $end

$scope module t1 $end
$var wire 1 . Addr [7] $end
$var wire 1 / Addr [6] $end
$var wire 1 0 Addr [5] $end
$var wire 1 1 Addr [4] $end
$var wire 1 2 Addr [3] $end
$var wire 1 3 Addr [2] $end
$var wire 1 4 Addr [1] $end
$var wire 1 5 Addr [0] $end
$var wire 1 6 Aluop [3] $end
$var wire 1 7 Aluop [2] $end
$var wire 1 8 Aluop [1] $end
$var wire 1 9 Aluop [0] $end
$var wire 1 : DatA [7] $end
$var wire 1 ; DatA [6] $end
$var wire 1 < DatA [5] $end
$var wire 1 = DatA [4] $end
$var wire 1 > DatA [3] $end
$var wire 1 ? DatA [2] $end
$var wire 1 @ DatA [1] $end
$var wire 1 A DatA [0] $end
$var wire 1 B DatB [7] $end
$var wire 1 C DatB [6] $end
$var wire 1 D DatB [5] $end
$var wire 1 E DatB [4] $end
$var wire 1 F DatB [3] $end
$var wire 1 G DatB [2] $end
$var wire 1 H DatB [1] $end
$var wire 1 I DatB [0] $end
$var wire 1 J Imm [2] $end
$var wire 1 K Imm [1] $end
$var wire 1 L Imm [0] $end
$var wire 1 M Jen $end
$var wire 1 N Jptr [4] $end
$var wire 1 O Jptr [3] $end
$var wire 1 P Jptr [2] $end
$var wire 1 Q Jptr [1] $end
$var wire 1 R Jptr [0] $end
$var wire 1 S Jump [5] $end
$var wire 1 T Jump [4] $end
$var wire 1 U Jump [3] $end
$var wire 1 V Jump [2] $end
$var wire 1 W Jump [1] $end
$var wire 1 X Jump [0] $end
$var wire 1 Y Ldr $end
$var wire 1 Z PC [5] $end
$var wire 1 [ PC [4] $end
$var wire 1 \ PC [3] $end
$var wire 1 ] PC [2] $end
$var wire 1 ^ PC [1] $end
$var wire 1 _ PC [0] $end
$var wire 1 ` Par $end
$var wire 1 a Ra [2] $end
$var wire 1 b Ra [1] $end
$var wire 1 c Ra [0] $end
$var wire 1 d Rb [2] $end
$var wire 1 e Rb [1] $end
$var wire 1 f Rb [0] $end
$var wire 1 g Rdat [7] $end
$var wire 1 h Rdat [6] $end
$var wire 1 i Rdat [5] $end
$var wire 1 j Rdat [4] $end
$var wire 1 k Rdat [3] $end
$var wire 1 l Rdat [2] $end
$var wire 1 m Rdat [1] $end
$var wire 1 n Rdat [0] $end
$var wire 1 o RdatA [7] $end
$var wire 1 p RdatA [6] $end
$var wire 1 q RdatA [5] $end
$var wire 1 r RdatA [4] $end
$var wire 1 s RdatA [3] $end
$var wire 1 t RdatA [2] $end
$var wire 1 u RdatA [1] $end
$var wire 1 v RdatA [0] $end
$var wire 1 w RdatB [7] $end
$var wire 1 x RdatB [6] $end
$var wire 1 y RdatB [5] $end
$var wire 1 z RdatB [4] $end
$var wire 1 { RdatB [3] $end
$var wire 1 | RdatB [2] $end
$var wire 1 } RdatB [1] $end
$var wire 1 ~ RdatB [0] $end
$var wire 1 !! Rslt [7] $end
$var wire 1 "! Rslt [6] $end
$var wire 1 #! Rslt [5] $end
$var wire 1 $! Rslt [4] $end
$var wire 1 %! Rslt [3] $end
$var wire 1 &! Rslt [2] $end
$var wire 1 '! Rslt [1] $end
$var wire 1 (! Rslt [0] $end
$var wire 1 )! SCo $end
$var wire 1 *! Str $end
$var wire 1 +! Wd [2] $end
$var wire 1 ,! Wd [1] $end
$var wire 1 -! Wd [0] $end
$var wire 1 .! WdatD [7] $end
$var wire 1 /! WdatD [6] $end
$var wire 1 0! WdatD [5] $end
$var wire 1 1! WdatD [4] $end
$var wire 1 2! WdatD [3] $end
$var wire 1 3! WdatD [2] $end
$var wire 1 4! WdatD [1] $end
$var wire 1 5! WdatD [0] $end
$var wire 1 6! WdatR [7] $end
$var wire 1 7! WdatR [6] $end
$var wire 1 8! WdatR [5] $end
$var wire 1 9! WdatR [4] $end
$var wire 1 :! WdatR [3] $end
$var wire 1 ;! WdatR [2] $end
$var wire 1 <! WdatR [1] $end
$var wire 1 =! WdatR [0] $end
$var wire 1 >! WenD $end
$var wire 1 ?! WenR $end
$var wire 1 @! Zero $end
$var wire 1 A! clk $end
$var wire 1 B! mach_code [8] $end
$var wire 1 C! mach_code [7] $end
$var wire 1 D! mach_code [6] $end
$var wire 1 E! mach_code [5] $end
$var wire 1 F! mach_code [4] $end
$var wire 1 G! mach_code [3] $end
$var wire 1 H! mach_code [2] $end
$var wire 1 I! mach_code [1] $end
$var wire 1 J! mach_code [0] $end
$var wire 1 K! reset $end
$var reg 1 L! done $end

$scope module A1 $end
$var wire 1 6 Aluop [3] $end
$var wire 1 7 Aluop [2] $end
$var wire 1 8 Aluop [1] $end
$var wire 1 9 Aluop [0] $end
$var wire 1 : DatA [7] $end
$var wire 1 ; DatA [6] $end
$var wire 1 < DatA [5] $end
$var wire 1 = DatA [4] $end
$var wire 1 > DatA [3] $end
$var wire 1 ? DatA [2] $end
$var wire 1 @ DatA [1] $end
$var wire 1 A DatA [0] $end
$var wire 1 B DatB [7] $end
$var wire 1 C DatB [6] $end
$var wire 1 D DatB [5] $end
$var wire 1 E DatB [4] $end
$var wire 1 F DatB [3] $end
$var wire 1 G DatB [2] $end
$var wire 1 H DatB [1] $end
$var wire 1 I DatB [0] $end
$var wire 1 J Imm [2] $end
$var wire 1 K Imm [1] $end
$var wire 1 L Imm [0] $end
$var reg 1 M! Jen $end
$var reg 1 N! Par $end
$var reg 8 O! Rslt [7:0] $end
$var reg 1 P! SCo $end
$var reg 1 Q! Zero $end
$var reg 3 R! signed_imm [2:0] $end
$upscope $end

$scope module C1 $end
$var wire 1 M Jen $end
$var wire 1 B! mach_code [8] $end
$var wire 1 C! mach_code [7] $end
$var wire 1 D! mach_code [6] $end
$var wire 1 E! mach_code [5] $end
$var wire 1 F! mach_code [4] $end
$var wire 1 G! mach_code [3] $end
$var wire 1 H! mach_code [2] $end
$var wire 1 I! mach_code [1] $end
$var wire 1 J! mach_code [0] $end
$var reg 4 S! Aluop [3:0] $end
$var reg 3 T! Imm [2:0] $end
$var reg 5 U! Jptr [4:0] $end
$var reg 1 V! Ldr $end
$var reg 3 W! Ra [2:0] $end
$var reg 3 X! Rb [2:0] $end
$var reg 1 Y! Str $end
$var reg 3 Z! Wd [2:0] $end
$var reg 1 [! WenD $end
$var reg 1 \! WenR $end
$upscope $end

$scope module IR1 $end
$var wire 1 Z PC [5] $end
$var wire 1 [ PC [4] $end
$var wire 1 \ PC [3] $end
$var wire 1 ] PC [2] $end
$var wire 1 ^ PC [1] $end
$var wire 1 _ PC [0] $end
$var reg 9 ]! mach_code [8:0] $end
$upscope $end

$scope module JL1 $end
$var wire 1 N Jptr [4] $end
$var wire 1 O Jptr [3] $end
$var wire 1 P Jptr [2] $end
$var wire 1 Q Jptr [1] $end
$var wire 1 R Jptr [0] $end
$var reg 6 ^! Jump [5:0] $end
$upscope $end

$scope module PC1 $end
$var wire 1 M Jen $end
$var wire 1 S Jump [5] $end
$var wire 1 T Jump [4] $end
$var wire 1 U Jump [3] $end
$var wire 1 V Jump [2] $end
$var wire 1 W Jump [1] $end
$var wire 1 X Jump [0] $end
$var wire 1 A! clk $end
$var wire 1 K! reset $end
$var reg 6 _! PC [5:0] $end
$upscope $end

$scope module RF1 $end
$var wire 1 a Ra [2] $end
$var wire 1 b Ra [1] $end
$var wire 1 c Ra [0] $end
$var wire 1 d Rb [2] $end
$var wire 1 e Rb [1] $end
$var wire 1 f Rb [0] $end
$var wire 1 o RdatA [7] $end
$var wire 1 p RdatA [6] $end
$var wire 1 q RdatA [5] $end
$var wire 1 r RdatA [4] $end
$var wire 1 s RdatA [3] $end
$var wire 1 t RdatA [2] $end
$var wire 1 u RdatA [1] $end
$var wire 1 v RdatA [0] $end
$var wire 1 w RdatB [7] $end
$var wire 1 x RdatB [6] $end
$var wire 1 y RdatB [5] $end
$var wire 1 z RdatB [4] $end
$var wire 1 { RdatB [3] $end
$var wire 1 | RdatB [2] $end
$var wire 1 } RdatB [1] $end
$var wire 1 ~ RdatB [0] $end
$var wire 1 +! Wd [2] $end
$var wire 1 ,! Wd [1] $end
$var wire 1 -! Wd [0] $end
$var wire 1 6! Wdat [7] $end
$var wire 1 7! Wdat [6] $end
$var wire 1 8! Wdat [5] $end
$var wire 1 9! Wdat [4] $end
$var wire 1 :! Wdat [3] $end
$var wire 1 ;! Wdat [2] $end
$var wire 1 <! Wdat [1] $end
$var wire 1 =! Wdat [0] $end
$var wire 1 ?! Wen $end
$var wire 1 A! clk $end
$upscope $end

$scope module dm $end
$var wire 1 . Addr [7] $end
$var wire 1 / Addr [6] $end
$var wire 1 0 Addr [5] $end
$var wire 1 1 Addr [4] $end
$var wire 1 2 Addr [3] $end
$var wire 1 3 Addr [2] $end
$var wire 1 4 Addr [1] $end
$var wire 1 5 Addr [0] $end
$var wire 1 .! WDat [7] $end
$var wire 1 /! WDat [6] $end
$var wire 1 0! WDat [5] $end
$var wire 1 1! WDat [4] $end
$var wire 1 2! WDat [3] $end
$var wire 1 3! WDat [2] $end
$var wire 1 4! WDat [1] $end
$var wire 1 5! WDat [0] $end
$var wire 1 >! Wen $end
$var wire 1 A! clk $end
$var reg 8 `! Rdat [7:0] $end
$upscope $end
$upscope $end
$upscope $end

$scope begin std $end
$upscope $end
$enddefinitions $end
#0
$dumpvars
x!
xX
xW
xV
xU
xT
xS
x_
x^
x]
x\
x[
xZ
xc
xb
xa
xf
xe
xd
x-!
x,!
x+!
x9
x8
x7
x6
xL
xK
xJ
xR
xQ
xP
xO
xN
xJ!
xI!
xH!
xG!
xF!
xE!
xD!
xC!
xB!
xA
x@
x?
x>
x=
x<
x;
x:
xI
xH
xG
xF
xE
xD
xC
xB
0(!
0'!
0&!
0%!
0$!
0#!
0"!
0!!
xv
xu
xt
xs
xr
xq
xp
xo
x~
x}
x|
x{
xz
xy
xx
xw
0=!
0<!
0;!
0:!
09!
08!
07!
06!
z5!
z4!
z3!
z2!
z1!
z0!
z/!
z.!
xn
xm
xl
xk
xj
xi
xh
xg
z5
z4
z3
z2
z1
z0
z/
z.
xM
0`
0)!
1@!
x?!
x>!
xY
x*!
1K!
0A!
bx "
bx #
bx $
bx %
bx &
bx '
bx (
0)
1*
bx +
bx ,
bx -
xL!
xM!
0N!
b0 O!
0P!
1Q!
bx R!
bx S!
bx T!
bx U!
xV!
bx W!
bx X!
xY!
bx Z!
x[!
x\!
bx ]!
bx ^!
bx _!
bx `!
$end
#50
1)
1A!
b0 _!
0_
0^
0]
0\
0[
0Z
b110100110 ]!
0J!
1I!
1H!
0G!
0F!
1E!
0D!
1C!
1B!
b100 W!
b110 X!
b111 S!
0f
1e
1d
0c
0b
1a
19
18
17
06
0M!
0M
#100
b10000 &
b0 #
0)
0A!
#101
b11010100100100 +
b101111010000001 ,
b1001 -
b1001 "
b1001 &
b0 (
b1 '
b1001 #
b0 %
b1 $
#102
b1101011000001001 ,
b1001 -
#103
b101011001100011 ,
b1000 -
b1000 "
b1000 &
b11 '
#104
b111101100001101 ,
b111 -
b111 "
b111 &
b100 '
#105
b1001100110001101 ,
b1000 -
b1000 "
#106
b1000010001100101 ,
b110 -
b110 "
b110 &
b110 '
#107
b101001000010010 ,
b1001 -
b1001 "
#108
b1110001100000001 ,
b1000 -
b1000 "
#109
b1100110100001101 ,
b1000 -
#110
b1111000101110110 ,
b110 -
b110 "
#111
b1100110100111101 ,
b1000 -
b1000 "
#112
b101011111101101 ,
b111 -
b111 "
#113
b1111011110001100 ,
b110 -
b110 "
#114
b1110100111111001 ,
b1011 -
b1011 "
b1011 #
b1110 $
#115
b10010011000110 ,
b110 -
b110 "
#116
b1000010011000101 ,
b1000 -
b1000 "
#117
b1101001010101010 ,
b1010 -
b1010 "
#118
b1111011111100101 ,
b110 -
b110 "
#119
b111001001110111 ,
b1000 -
b1000 "
#120
b1101011000010010 ,
b1001 -
b1001 "
#121
b1101101110001111 ,
b1011 -
b1011 "
#122
b110100111110010 ,
b1001 -
b1001 "
#123
b1001011011001110 ,
b1001 -
#124
b111101011101000 ,
b1001 -
#125
b100111011000101 ,
b1010 -
b1010 "
#126
b100100101011100 ,
b1001 -
b1001 "
#127
b10100010111101 ,
b1000 -
b1000 "
#128
b101100000101101 ,
b111 -
b111 "
#129
b10011001100101 ,
b101 -
b101 "
b101 &
b11101 '
#130
b110001001100011 ,
b1001 -
b1001 "
#131
b1000011100001010 ,
b1000 -
b1000 "
#132
b101111010000001 +
b1101011000001001 ,
b100 -
b100 "
b100 &
b1 (
b10 '
#133
b101011001100011 ,
b101 -
b101 "
#134
b111101100001101 ,
b110 -
b110 "
#135
b1001100110001101 ,
b111 -
b111 "
#136
b1000010001100101 ,
b1001 -
b1001 "
#137
b101001000010010 ,
b110 -
b110 "
#138
b1110001100000001 ,
b111 -
b111 "
#139
b1100110100001101 ,
b111 -
#140
b1111000101110110 ,
b1101 -
b1101 "
b1101 #
b1 %
b1010 $
#141
b1100110100111101 ,
b1001 -
b1001 "
#142
b101011111101101 ,
b110 -
b110 "
#143
b1111011110001100 ,
b111 -
b111 "
#144
b1110100111111001 ,
b1010 -
b1010 "
#145
b10010011000110 ,
b1001 -
b1001 "
#146
b1000010011000101 ,
b111 -
b111 "
#147
b1101001010101010 ,
b111 -
#148
b1111011111100101 ,
b111 -
#149
b111001001110111 ,
b1001 -
b1001 "
#150
1)
b1101011000010010 ,
b110 -
b110 "
1A!
#151
b1101101110001111 ,
b110 -
#152
b110100111110010 ,
b1010 -
b1010 "
#153
b1001011011001110 ,
b1000 -
b1000 "
#154
b111101011101000 ,
b110 -
b110 "
#155
b100111011000101 ,
b11 -
b11 "
b11 &
b11001 '
#156
b100100101011100 ,
b1010 -
b1010 "
#157
b10100010111101 ,
b1001 -
b1001 "
#158
b101100000101101 ,
b110 -
b110 "
#159
b10011001100101 ,
b1000 -
b1000 "
#160
b110001001100011 ,
b1000 -
#161
b1000011100001010 ,
b1001 -
b1001 "
#162
b1101011000001001 +
b101011001100011 ,
b101 -
b101 "
#163
b111101100001101 ,
b110 -
b110 "
#164
b1001100110001101 ,
b111 -
b111 "
#165
b1000010001100101 ,
b111 -
#166
b101001000010010 ,
b110 -
b110 "
#167
b1110001100000001 ,
b101 -
b101 "
#168
b1100110100001101 ,
b101 -
#169
b1111000101110110 ,
b1011 -
b1011 "
#170
b1100110100111101 ,
b111 -
b111 "
#171
b101011111101101 ,
b110 -
b110 "
#172
b1111011110001100 ,
b101 -
b101 "
#173
b1110100111111001 ,
b1010 -
b1010 "
#174
b10010011000110 ,
b1011 -
b1011 "
#175
b1000010011000101 ,
b111 -
b111 "
#176
b1101001010101010 ,
b101 -
b101 "
#177
b1111011111100101 ,
b111 -
b111 "
#178
b111001001110111 ,
b1001 -
b1001 "
#179
b1101011000010010 ,
b100 -
b100 "
#180
b1101101110001111 ,
b110 -
b110 "
#181
b110100111110010 ,
b1110 -
b1110 "
b1110 #
b10 %
b10110 $
#182
b1001011011001110 ,
b110 -
b110 "
#183
b111101011101000 ,
b1000 -
b1000 "
#184
b100111011000101 ,
b111 -
b111 "
#185
b100100101011100 ,
b1010 -
b1010 "
#186
b10100010111101 ,
b1011 -
b1011 "
#187
b101100000101101 ,
b110 -
b110 "
#188
b10011001100101 ,
b1000 -
b1000 "
#189
b110001001100011 ,
b1000 -
#190
b1000011100001010 ,
b101 -
b101 "
#191
b101011001100011 +
b111101100001101 ,
b1001 -
b1001 "
#192
b1001100110001101 ,
b1100 -
b1100 "
#193
b1000010001100101 ,
b110 -
b110 "
#194
b101001000010010 ,
b101 -
b101 "
#195
b1110001100000001 ,
b1000 -
b1000 "
#196
b1100110100001101 ,
b1010 -
b1010 "
#197
b1111000101110110 ,
b1000 -
b1000 "
#198
b1100110100111101 ,
b1010 -
b1010 "
#199
b101011111101101 ,
b101 -
b101 "
#200
0)
b1111011110001100 ,
b1010 -
b1010 "
0A!
#201
b1110100111111001 ,
b1011 -
b1011 "
#202
b10010011000110 ,
b1000 -
b1000 "
#203
b1000010011000101 ,
b1000 -
#204
b1101001010101010 ,
b110 -
b110 "
#205
b1111011111100101 ,
b110 -
#206
b111001001110111 ,
b100 -
b100 "
#207
b1101011000010010 ,
b101 -
b101 "
#208
b1101101110001111 ,
b1001 -
b1001 "
#209
b110100111110010 ,
b1001 -
#210
b1001011011001110 ,
b111 -
b111 "
#211
b111101011101000 ,
b111 -
#212
b100111011000101 ,
b110 -
b110 "
#213
b100100101011100 ,
b1011 -
b1011 "
#214
b10100010111101 ,
b1100 -
b1100 "
#215
b101100000101101 ,
b111 -
b111 "
#216
b10011001100101 ,
b101 -
b101 "
#217
b110001001100011 ,
b11 -
b11 "
#218
b1000011100001010 ,
b1000 -
b1000 "
#219
b111101100001101 +
b1001100110001101 ,
b101 -
b101 "
#220
b1000010001100101 ,
b1011 -
b1011 "
#221
b101001000010010 ,
b1000 -
b1000 "
#222
b1110001100000001 ,
b101 -
b101 "
#223
b1100110100001101 ,
b101 -
#224
b1111000101110110 ,
b1001 -
b1001 "
#225
b1100110100111101 ,
b111 -
b111 "
#226
b101011111101101 ,
b110 -
b110 "
#227
b1111011110001100 ,
b101 -
b101 "
#228
b1110100111111001 ,
b1000 -
b1000 "
#229
b10010011000110 ,
b1011 -
b1011 "
#230
b1000010011000101 ,
b1011 -
#231
b1101001010101010 ,
b1001 -
b1001 "
#232
b1111011111100101 ,
b111 -
b111 "
#233
b111001001110111 ,
b111 -
#234
b1101011000010010 ,
b1010 -
b1010 "
#235
b1101101110001111 ,
b100 -
b100 "
#236
b110100111110010 ,
b1010 -
b1010 "
#237
b1001011011001110 ,
b1010 -
#238
b111101011101000 ,
b110 -
b110 "
#239
b100111011000101 ,
b111 -
b111 "
#240
b100100101011100 ,
b110 -
b110 "
#241
b10100010111101 ,
b111 -
b111 "
#242
b101100000101101 ,
b100 -
b100 "
#243
b10011001100101 ,
b1000 -
b1000 "
#244
b110001001100011 ,
b1000 -
#245
b1000011100001010 ,
b1001 -
b1001 "
#246
b1001100110001101 +
b1000010001100101 ,
b1000 -
b1000 "
#247
b101001000010010 ,
b1011 -
b1011 "
#248
b1110001100000001 ,
b1000 -
b1000 "
#249
b1100110100001101 ,
b100 -
b100 "
#250
1)
b1111000101110110 ,
b1010 -
b1010 "
1A!
#251
b1100110100111101 ,
b110 -
b110 "
#252
b101011111101101 ,
b111 -
b111 "
#253
b1111011110001100 ,
b110 -
b110 "
#254
b1110100111111001 ,
b111 -
b111 "
#255
b10010011000110 ,
b1010 -
b1010 "
#256
b1000010011000101 ,
b110 -
b110 "
#257
b1101001010101010 ,
b1000 -
b1000 "
#258
b1111011111100101 ,
b1000 -
